Workbook

Sheet Cover
A1: HAVELLS INDIA LIMITED
A2: Hypothetical Leveraged Buyout Model
A4: READ THIS FIRST
A5: Havells is NOT a realistic LBO target. The promoter group (QRG Investments and Holdings) holds approximately 59% of the company, and a take-private at this scale (~INR 70,000 Cr market cap) would be one of the largest buyouts ever attempted in India. India's bank-dominated debt market also would not support US-style leverage multiples. This model is an explicit hypothetical exercise in LBO mechanics on a clean, well-disclosed dataset: it is not a deal thesis and should never be presented as one. State this plainly in any memo or interview discussion of this model, before the numbers.
A12: Companion model | B12: Operating forecast (revenue, EBITDA, D&A, capex, working capital) is carried over from Havells_3Statement_DCF_Model.xlsx, base case, FY27E-FY31E.
A14: Entry point | B14: Start of FY27E (i.e. transaction closes using FY26A actuals as the LTM reference).
A16: Debt structure | B16: Single senior secured term loan only, by design, no mezzanine tranche. Simpler and cleaner for a first LBO build; a real deal at this leverage would likely be single-tranche anyway.
A18: Leverage | B18: India-adjusted and conservative relative to US benchmarks (which run 4-6x EBITDA total in 2026): this model anchors to roughly 2.5-3x total leverage, reflecting India's bank-dominated, lower-risk-tolerance debt market.
A20: Units | B20: INR crore unless stated otherwise
A22: Colour convention | B22: BLUE = hardcoded input | BLACK = formula on this sheet | GREEN = link from another sheet | YELLOW FILL = assumption requiring justification
A24: Disclaimer | B24: Educational exercise. Not investment research, not a deal recommendation, not investment advice.

Sheet Assumptions
A1: TRANSACTION ASSUMPTIONS
A2: Every yellow cell is an input you own and must justify.
A4: ENTRY
A5: Entry EBITDA, FY26A (LTM at close) | B5: 2213 | D5: Reported FY26A EBITDA. Source: Havells Information Update, Q4 FY26.
A6: Illustrative entry EV/EBITDA multiple | B6: 12 | D6: Deliberately BELOW Havells' actual public trading multiple (~33x EV/EBITDA at a ~INR 1,190 share price); see memo cell below. A real buyer would need to pay near the trading multiple plus a control premium; at that price, no plausible debt-funded structure clears an acceptable IRR. Run the Sensitivity tab at higher entry multiples to see this directly.
A7: Memo: current public EV/EBITDA multiple (context only) | B7: 32.8 | D7: For contrast only; not used in any formula. Illustrates why Havells does not clear as a real LBO at its traded price.
A8: Entry net cash (FY26A): cash & bank balances | B8: 2351 | D8: Havells' FY26A closing cash and other bank balances.
A9: Entry net cash (FY26A): lease liabilities (debt-like) | B9: -265 | D9: The only debt-like item on Havells' balance sheet.
A10: Entry net cash, total | B10: =B8+B9 -> 2086
A12: FINANCING
A13: Total leverage (x FY26A EBITDA) | B13: 2.75 | D13: India-adjusted and conservative vs. the 4-6x total typical in US buyouts today: this reflects a bank-dominated, lower-risk-tolerance Indian debt market.
A14: Senior term loan interest rate (all-in) | B14: 0.105 | D14: Illustrative Indian large-cap secured lending rate. Cite an actual benchmark (SBI MCLR + spread, or a comparable rated NCD) before presenting this.
A15: Mandatory amortisation (% of original principal, per year) | B15: 0.05 | D15: Standard term-loan amortisation schedule.
A16: Cash sweep (% of excess free cash flow swept to debt paydown) | B16: 1 | D16: 100% cash sweep is aggressive but standard base-case LBO practice; a covenant-lite deal might use less.
A17: Transaction fees (% of entry EV) | B17: 0.02 | D17: Advisory, legal and financing fees: a standard planning assumption.
A18: Target cash swept to fund the deal at close (% of entry cash) | B18: 1 | D18: Assumes the target's own cash pile is used to partially fund its own acquisition: standard practice for a cash-rich target, and especially relevant here given Havells carries INR 2,351 Cr of cash. NOTE: this leaves NO cash buffer post-close, which shows up as tight or negative free cash flow in the debt schedule's early years; see memo.
A20: OPERATING & TAX (carried over from the 3-statement DCF model)
A21: Effective tax rate | B21: 0.252 | D21: Same as the companion DCF model, statutory rate under the concessional regime.
A23: EXIT
A24: Hold period (years) | B24: 5 | D24: FY27E to FY31E, matching the DCF's forecast horizon.
A25: Exit EV/EBITDA multiple | B25: 12 | D25: Base case: no multiple expansion assumed (same as entry). Test expansion/contraction on the Sensitivity tab.

Sheet Sources & Uses
A1: SOURCES & USES
A2: The two columns must tie out exactly. INR crore.
A4: ENTRY VALUATION
A5: Entry EBITDA (FY26A) | B5: =Assumptions!$B$5 -> 2213
A6: x Entry EV/EBITDA multiple | B6: =Assumptions!$B$6 -> 12
A7: Entry Enterprise Value | B7: =B5*B6 -> 26556
A8: Add: entry net cash (buyer pays for the cash pile too) | B8: =Assumptions!$B$10 -> 2086
A9: Equity Purchase Price | B9: =B7+B8 -> 28642
A12: USES
A13: Purchase of equity | B13: =B9 -> 28642
A14: Transaction fees | B14: =B7*Assumptions!$B$17 -> 531.12
A15: TOTAL USES | B15: =SUM(B13:B14) -> 29173.12
A18: SOURCES
A19: New senior term loan | B19: =Assumptions!$B$13*B5 -> 6085.75
A20: Target's own cash, swept to fund the deal at close | B20: =Assumptions!$B$8*Assumptions!$B$18 -> 2351
A21: Sponsor equity (plug) | B21: =B15-B19-B20 -> 20736.37
A22: TOTAL SOURCES | B22: =SUM(B19:B21) -> 29173.12
A24: CHECK (Sources - Uses, must be zero) | B24: =B22-B15 -> 0
A27: Implied leverage at close | B27: =B19/B5 -> 2.75
A28: Sponsor equity as % of total sources | B28: =B21/B22 -> 0.71080399
A30: NOTE
A31: This model funds the deal by sweeping 100% of Havells' own FY26A cash pile at close. That leaves zero cash buffer entering FY27E; a real deal would likely retain some minimum operating cash. Watch the Debt Schedule tab for tight or negative free cash flow in the early years as a direct consequence of this assumption; it is a genuine limitation, not a modelling error.

Sheet Operating Model
A1: OPERATING MODEL (carried over from the 3-statement DCF model)
A2: Base case FY27E-FY31E. Source: Havells_3Statement_DCF_Model.xlsx, IS and Schedules tabs.
A4: INR crore | B4: FY27E | C4: FY28E | D4: FY29E | E4: FY30E | F4: FY31E
A6: Net revenue | B6: 25127 | C6: 28151 | D6: 31310 | E6: 34439 | F6: 37595
A7: EBITDA | B7: 2511 | C7: 2869 | D7: 3230 | E7: 3520 | F7: 3852
A8: Depreciation & amortisation | B8: 503 | C8: 591 | D8: 689 | E8: 758 | F8: 865
A9: Capital expenditure | B9: 1256 | C9: 1267 | D9: 1252 | E9: 1309 | F9: 1316
A10: Increase in net working capital | B10: 407 | C10: 323 | D10: 338 | E10: 334 | F10: 337
A12: EBIT = EBITDA - D&A | B12: =B7-B8 -> 2008 | C12: =C7-C8 -> 2278 | D12: =D7-D8 -> 2541 | E12: =E7-E8 -> 2762 | F12: =F7-F8 -> 2987
A13: EBITDA margin | B13: =B7/B6 -> 0.099932344 | C13: =C7/C6 -> 0.10191467 | D13: =D7/D6 -> 0.10316193 | E13: =E7/E6 -> 0.1022097 | F13: =F7/F6 -> 0.10246043

Sheet Debt Schedule
A1: DEBT SCHEDULE: SINGLE SENIOR TERM LOAN
A2: Mandatory amortisation of original principal, plus a 100% cash sweep of any free cash flow left over. Circularity (interest depends on the average balance, which depends on the sweep, which depends on free cash flow, which depends on interest) is handled with a circuit breaker, same as the DCF model.
A3: Enable File > Options > Formulas > Iterative Calculation before opening in Excel.
A5: INR crore | B5: FY27E | C5: FY28E | D5: FY29E | E5: FY30E | F5: FY31E
A7: EBIT | B7: ='Operating Model'!B$12 -> 2008 | C7: ='Operating Model'!C$12 -> 2278 | D7: ='Operating Model'!D$12 -> 2541 | E7: ='Operating Model'!E$12 -> 2762 | F7: ='Operating Model'!F$12 -> 2987
A8: Less: cash tax at operating tax rate | B8: =-B7*Assumptions!$B$21 -> -506.016 | C8: =-C7*Assumptions!$B$21 -> -574.056 | D8: =-D7*Assumptions!$B$21 -> -640.332 | E8: =-E7*Assumptions!$B$21 -> -696.024 | F8: =-F7*Assumptions!$B$21 -> -752.724
A9: NOPAT | B9: =B7+B8 -> 1501.984 | C9: =C7+C8 -> 1703.944 | D9: =D7+D8 -> 1900.668 | E9: =E7+E8 -> 2065.976 | F9: =F7+F8 -> 2234.276
A11: Add: depreciation & amortisation | B11: ='Operating Model'!B$8 -> 503 | C11: ='Operating Model'!C$8 -> 591 | D11: ='Operating Model'!D$8 -> 689 | E11: ='Operating Model'!E$8 -> 758 | F11: ='Operating Model'!F$8 -> 865
A12: Less: capital expenditure | B12: =-'Operating Model'!B$9 -> -1256 | C12: =-'Operating Model'!C$9 -> -1267 | D12: =-'Operating Model'!D$9 -> -1252 | E12: =-'Operating Model'!E$9 -> -1309 | F12: =-'Operating Model'!F$9 -> -1316
A13: Less: increase in net working capital | B13: =-'Operating Model'!B$10 -> -407 | C13: =-'Operating Model'!C$10 -> -323 | D13: =-'Operating Model'!D$10 -> -338 | E13: =-'Operating Model'!E$10 -> -334 | F13: =-'Operating Model'!F$10 -> -337
A15: Circuit breaker (0 = normal, 1 = break circularity) | B15: 0 | C15: =$B$15 -> 0 | D15: =$B$15 -> 0 | E15: =$B$15 -> 0 | F15: =$B$15 -> 0
A17: Opening term loan balance | B17: ='Sources & Uses'!$B$19 -> 6085.75 | C17: =B23 -> 5781.4625 | D17: =C23 -> 5477.175 | E17: =D23 -> 5036.6353 | F17: =E23 -> 4368.5309
A18: Interest expense (average balance x rate) | B18: =IF(B$15=1,0,AVERAGE(B17,B17-B20)*Assumptions!$B$14) -> 623.02866 | C18: =IF(C$15=1,0,AVERAGE(C17,C17-C20)*Assumptions!$B$14) -> 591.07847 | D18: =IF(D$15=1,0,AVERAGE(D17,D17-D20)*Assumptions!$B$14) -> 559.12828 | E18: =IF(E$15=1,0,AVERAGE(E17,E17-E20)*Assumptions!$B$14) -> 512.87161 | F18: =IF(F$15=1,0,AVERAGE(F17,F17-F20)*Assumptions!$B$14) -> 442.72065
A19: Cash available before mandatory amortisation | B19: =B9+B11+B12+B13-B18 -> -281.04466 | C19: =C9+C11+C12+C13-C18 -> 113.86553 | D19: =D9+D11+D12+D13-D18 -> 440.53972 | E19: =E9+E11+E12+E13-E18 -> 668.10439 | F19: =F9+F11+F12+F13-F18 -> 1003.5554
A20: Less: mandatory amortisation | B20: =MIN(B17,'Sources & Uses'!$B$19*Assumptions!$B$15) -> 304.2875 | C20: =MIN(C17,'Sources & Uses'!$B$19*Assumptions!$B$15) -> 304.2875 | D20: =MIN(D17,'Sources & Uses'!$B$19*Assumptions!$B$15) -> 304.2875 | E20: =MIN(E17,'Sources & Uses'!$B$19*Assumptions!$B$15) -> 304.2875 | F20: =MIN(F17,'Sources & Uses'!$B$19*Assumptions!$B$15) -> 304.2875
A21: Cash available for optional prepayment (sweep) | B21: =MAX(B19-B20,0) -> 0 | C21: =MAX(C19-C20,0) -> 0 | D21: =MAX(D19-D20,0) -> 136.25222 | E21: =MAX(E19-E20,0) -> 363.81689 | F21: =MAX(F19-F20,0) -> 699.26785
A22: Optional prepayment (cash sweep) | B22: =MIN(B21,B17-B20)*Assumptions!$B$16 -> 0 | C22: =MIN(C21,C17-C20)*Assumptions!$B$16 -> 0 | D22: =MIN(D21,D17-D20)*Assumptions!$B$16 -> 136.25222 | E22: =MIN(E21,E17-E20)*Assumptions!$B$16 -> 363.81689 | F22: =MIN(F21,F17-F20)*Assumptions!$B$16 -> 699.26785
A23: Closing term loan balance | B23: =B17-B20-B22 -> 5781.4625 | C23: =C17-C20-C22 -> 5477.175 | D23: =D17-D20-D22 -> 5036.6353 | E23: =E17-E20-E22 -> 4368.5309 | F23: =F17-F20-F22 -> 3364.9755
A25: Excess cash after full debt paydown (accumulates) | B25: =MAX(B19-B20-B22,0) -> 0 | C25: =MAX(C19-C20-C22,0)+B25 -> 0 | D25: =MAX(D19-D20-D22,0)+C25 -> 0 | E25: =MAX(E19-E20-E22,0)+D25 -> 0 | F25: =MAX(F19-F20-F22,0)+E25 -> 0
A27: NOTE ON EARLY-YEAR CASH FLOW
A28: Because the target's entire cash pile was swept to fund the deal (Sources & Uses), there is no buffer entering FY27E. Havells' near-term capex is elevated (capacity additions carried over from the DCF forecast) relative to FY27E EBITDA, so 'cash available before mandatory amortisation' may be tight or negative in the first year or two. This model does not include a revolving credit facility to plug a shortfall: a genuine simplification, and a natural next extension.

Sheet Returns Analysis
A1: RETURNS ANALYSIS
A2: Clean end-of-period exit: no interim distributions assumed. INR crore.
A4: ENTRY
A5: Sponsor equity invested | B5: ='Sources & Uses'!$B$21 -> 20736.37
A7: EXIT (end of FY31E, after 5-year hold)
A8: Exit-year EBITDA (FY31E) | B8: ='Operating Model'!$F$7 -> 3852
A9: x Exit EV/EBITDA multiple | B9: =Assumptions!$B$25 -> 12
A10: Exit Enterprise Value | B10: =B8*B9 -> 46224
A11: Less: closing term loan balance | B11: =-'Debt Schedule'!$F$23 -> -3364.9755
A12: Add: accumulated excess cash | B12: ='Debt Schedule'!$F$25 -> 0
A13: Exit Equity Value | B13: =B10+B11+B12 -> 42859.024
A16: RETURNS
A17: MOIC (exit equity / entry equity) | B17: =B13/B5 -> 2.0668528
A18: Hold period (years) | B18: =Assumptions!$B$24 -> 5
A19: IRR = MOIC^(1/years) - 1 | B19: =B17^(1/B18)-1 -> 0.15627706
A22: RETURNS BRIDGE (decomposing the IRR)
A23: Entry equity value | B23: =B5 -> 20736.37
A24: + EBITDA growth (at entry multiple) | B24: =(B8-'Operating Model'!$B$7)*Assumptions!$B$6 -> 16092
A25: + Multiple change (exit EBITDA x change in multiple) | B25: =B8*(B9-Assumptions!$B$6) -> 0
A26: + Deleveraging & cash generation | B26: =B13-B23-B24-B25 -> 6030.6545
A27: Exit equity value (check, should equal B13) | B27: =SUM(B23:B26) -> 42859.024
A28: Check (B27 - B13, must be zero) | B28: =B27-B13 -> 0

Sheet Sensitivity
A1: SENSITIVITY: ENTRY MULTIPLE x EXIT MULTIPLE
A2: IRR at each combination. Note how quickly returns collapse as the entry multiple rises toward Havells' actual public trading multiple (~33x): this is the mechanical reason a real-world buyout at the traded price would not clear an acceptable return.
B5: Exit multiple → / Entry multiple ↓ | C5: 8.0x | D5: 10.0x | E5: 12.0x | F5: 15.0x | G5: 20.0x
B6: 8.0x | C6: =IFERROR((((('Operating Model'!$F$7*8)-'Debt Schedule'!$F$23+'Debt Schedule'!$F$25)/(((('Sources & Uses'!$B$5*8)+Assumptions!$B$10)+(('Sources & Uses'!$B$5*8)*Assumptions!$B$17))-(Assumptions!$B$13*'Sources & Uses'!$B$5)-(Assumptions!$B$8*Assumptions!$B$18)))^(1/Assumptions!$B$24)-1),NA()) -> 0.18582374 | D6: =IFERROR((((('Operating Model'!$F$7*10)-'Debt Schedule'!$F$23+'Debt Schedule'!$F$25)/(((('Sources & Uses'!$B$5*8)+Assumptions!$B$10)+(('Sources & Uses'!$B$5*8)*Assumptions!$B$17))-(Assumptions!$B$13*'Sources & Uses'!$B$5)-(Assumptions!$B$8*Assumptions!$B$18)))^(1/Assumptions!$B$24)-1),NA()) -> 0.24596519 | E6: =IFERROR((((('Operating Model'!$F$7*12)-'Debt Schedule'!$F$23+'Debt Schedule'!$F$25)/(((('Sources & Uses'!$B$5*8)+Assumptions!$B$10)+(('Sources & Uses'!$B$5*8)*Assumptions!$B$17))-(Assumptions!$B$13*'Sources & Uses'!$B$5)-(Assumptions!$B$8*Assumptions!$B$18)))^(1/Assumptions!$B$24)-1),NA()) -> 0.29633392 | F6: =IFERROR((((('Operating Model'!$F$7*15)-'Debt Schedule'!$F$23+'Debt Schedule'!$F$25)/(((('Sources & Uses'!$B$5*8)+Assumptions!$B$10)+(('Sources & Uses'!$B$5*8)*Assumptions!$B$17))-(Assumptions!$B$13*'Sources & Uses'!$B$5)-(Assumptions!$B$8*Assumptions!$B$18)))^(1/Assumptions!$B$24)-1),NA()) -> 0.35972848 | G6: =IFERROR((((('Operating Model'!$F$7*20)-'Debt Schedule'!$F$23+'Debt Schedule'!$F$25)/(((('Sources & Uses'!$B$5*8)+Assumptions!$B$10)+(('Sources & Uses'!$B$5*8)*Assumptions!$B$17))-(Assumptions!$B$13*'Sources & Uses'!$B$5)-(Assumptions!$B$8*Assumptions!$B$18)))^(1/Assumptions!$B$24)-1),NA()) -> 0.44468275
B7: 10.0x | C7: =IFERROR((((('Operating Model'!$F$7*8)-'Debt Schedule'!$F$23+'Debt Schedule'!$F$25)/(((('Sources & Uses'!$B$5*10)+Assumptions!$B$10)+(('Sources & Uses'!$B$5*10)*Assumptions!$B$17))-(Assumptions!$B$13*'Sources & Uses'!$B$5)-(Assumptions!$B$8*Assumptions!$B$18)))^(1/Assumptions!$B$24)-1),NA()) -> 0.11094264 | D7: =IFERROR((((('Operating Model'!$F$7*10)-'Debt Schedule'!$F$23+'Debt Schedule'!$F$25)/(((('Sources & Uses'!$B$5*10)+Assumptions!$B$10)+(('Sources & Uses'!$B$5*10)*Assumptions!$B$17))-(Assumptions!$B$13*'Sources & Uses'!$B$5)-(Assumptions!$B$8*Assumptions!$B$18)))^(1/Assumptions!$B$24)-1),NA()) -> 0.16728634 | E7: =IFERROR((((('Operating Model'!$F$7*12)-'Debt Schedule'!$F$23+'Debt Schedule'!$F$25)/(((('Sources & Uses'!$B$5*10)+Assumptions!$B$10)+(('Sources & Uses'!$B$5*10)*Assumptions!$B$17))-(Assumptions!$B$13*'Sources & Uses'!$B$5)-(Assumptions!$B$8*Assumptions!$B$18)))^(1/Assumptions!$B$24)-1),NA()) -> 0.21447444 | F7: =IFERROR((((('Operating Model'!$F$7*15)-'Debt Schedule'!$F$23+'Debt Schedule'!$F$25)/(((('Sources & Uses'!$B$5*10)+Assumptions!$B$10)+(('Sources & Uses'!$B$5*10)*Assumptions!$B$17))-(Assumptions!$B$13*'Sources & Uses'!$B$5)-(Assumptions!$B$8*Assumptions!$B$18)))^(1/Assumptions!$B$24)-1),NA()) -> 0.27386583 | G7: =IFERROR((((('Operating Model'!$F$7*20)-'Debt Schedule'!$F$23+'Debt Schedule'!$F$25)/(((('Sources & Uses'!$B$5*10)+Assumptions!$B$10)+(('Sources & Uses'!$B$5*10)*Assumptions!$B$17))-(Assumptions!$B$13*'Sources & Uses'!$B$5)-(Assumptions!$B$8*Assumptions!$B$18)))^(1/Assumptions!$B$24)-1),NA()) -> 0.3534555
B8: 12.0x | C8: =IFERROR((((('Operating Model'!$F$7*8)-'Debt Schedule'!$F$23+'Debt Schedule'!$F$25)/(((('Sources & Uses'!$B$5*12)+Assumptions!$B$10)+(('Sources & Uses'!$B$5*12)*Assumptions!$B$17))-(Assumptions!$B$13*'Sources & Uses'!$B$5)-(Assumptions!$B$8*Assumptions!$B$18)))^(1/Assumptions!$B$24)-1),NA()) -> 0.057706479 | D8: =IFERROR((((('Operating Model'!$F$7*10)-'Debt Schedule'!$F$23+'Debt Schedule'!$F$25)/(((('Sources & Uses'!$B$5*12)+Assumptions!$B$10)+(('Sources & Uses'!$B$5*12)*Assumptions!$B$17))-(Assumptions!$B$13*'Sources & Uses'!$B$5)-(Assumptions!$B$8*Assumptions!$B$18)))^(1/Assumptions!$B$24)-1),NA()) -> 0.11135021 | E8: =IFERROR((((('Operating Model'!$F$7*12)-'Debt Schedule'!$F$23+'Debt Schedule'!$F$25)/(((('Sources & Uses'!$B$5*12)+Assumptions!$B$10)+(('Sources & Uses'!$B$5*12)*Assumptions!$B$17))-(Assumptions!$B$13*'Sources & Uses'!$B$5)-(Assumptions!$B$8*Assumptions!$B$18)))^(1/Assumptions!$B$24)-1),NA()) -> 0.15627706 | F8: =IFERROR((((('Operating Model'!$F$7*15)-'Debt Schedule'!$F$23+'Debt Schedule'!$F$25)/(((('Sources & Uses'!$B$5*12)+Assumptions!$B$10)+(('Sources & Uses'!$B$5*12)*Assumptions!$B$17))-(Assumptions!$B$13*'Sources & Uses'!$B$5)-(Assumptions!$B$8*Assumptions!$B$18)))^(1/Assumptions!$B$24)-1),NA()) -> 0.21282243 | G8: =IFERROR((((('Operating Model'!$F$7*20)-'Debt Schedule'!$F$23+'Debt Schedule'!$F$25)/(((('Sources & Uses'!$B$5*12)+Assumptions!$B$10)+(('Sources & Uses'!$B$5*12)*Assumptions!$B$17))-(Assumptions!$B$13*'Sources & Uses'!$B$5)-(Assumptions!$B$8*Assumptions!$B$18)))^(1/Assumptions!$B$24)-1),NA()) -> 0.28859817
B9: 15.0x | C9: =IFERROR((((('Operating Model'!$F$7*8)-'Debt Schedule'!$F$23+'Debt Schedule'!$F$25)/(((('Sources & Uses'!$B$5*15)+Assumptions!$B$10)+(('Sources & Uses'!$B$5*15)*Assumptions!$B$17))-(Assumptions!$B$13*'Sources & Uses'!$B$5)-(Assumptions!$B$8*Assumptions!$B$18)))^(1/Assumptions!$B$24)-1),NA()) -> -0.00041568083 | D9: =IFERROR((((('Operating Model'!$F$7*10)-'Debt Schedule'!$F$23+'Debt Schedule'!$F$25)/(((('Sources & Uses'!$B$5*15)+Assumptions!$B$10)+(('Sources & Uses'!$B$5*15)*Assumptions!$B$17))-(Assumptions!$B$13*'Sources & Uses'!$B$5)-(Assumptions!$B$8*Assumptions!$B$18)))^(1/Assumptions!$B$24)-1),NA()) -> 0.050280263 | E9: =IFERROR((((('Operating Model'!$F$7*12)-'Debt Schedule'!$F$23+'Debt Schedule'!$F$25)/(((('Sources & Uses'!$B$5*15)+Assumptions!$B$10)+(('Sources & Uses'!$B$5*15)*Assumptions!$B$17))-(Assumptions!$B$13*'Sources & Uses'!$B$5)-(Assumptions!$B$8*Assumptions!$B$18)))^(1/Assumptions!$B$24)-1),NA()) -> 0.092738336 | F9: =IFERROR((((('Operating Model'!$F$7*15)-'Debt Schedule'!$F$23+'Debt Schedule'!$F$25)/(((('Sources & Uses'!$B$5*15)+Assumptions!$B$10)+(('Sources & Uses'!$B$5*15)*Assumptions!$B$17))-(Assumptions!$B$13*'Sources & Uses'!$B$5)-(Assumptions!$B$8*Assumptions!$B$18)))^(1/Assumptions!$B$24)-1),NA()) -> 0.14617647 | G9: =IFERROR((((('Operating Model'!$F$7*20)-'Debt Schedule'!$F$23+'Debt Schedule'!$F$25)/(((('Sources & Uses'!$B$5*15)+Assumptions!$B$10)+(('Sources & Uses'!$B$5*15)*Assumptions!$B$17))-(Assumptions!$B$13*'Sources & Uses'!$B$5)-(Assumptions!$B$8*Assumptions!$B$18)))^(1/Assumptions!$B$24)-1),NA()) -> 0.21778825
B10: 20.0x | C10: =IFERROR((((('Operating Model'!$F$7*8)-'Debt Schedule'!$F$23+'Debt Schedule'!$F$25)/(((('Sources & Uses'!$B$5*20)+Assumptions!$B$10)+(('Sources & Uses'!$B$5*20)*Assumptions!$B$17))-(Assumptions!$B$13*'Sources & Uses'!$B$5)-(Assumptions!$B$8*Assumptions!$B$18)))^(1/Assumptions!$B$24)-1),NA()) -> -0.066836396 | D10: =IFERROR((((('Operating Model'!$F$7*10)-'Debt Schedule'!$F$23+'Debt Schedule'!$F$25)/(((('Sources & Uses'!$B$5*20)+Assumptions!$B$10)+(('Sources & Uses'!$B$5*20)*Assumptions!$B$17))-(Assumptions!$B$13*'Sources & Uses'!$B$5)-(Assumptions!$B$8*Assumptions!$B$18)))^(1/Assumptions!$B$24)-1),NA()) -> -0.019509114 | E10: =IFERROR((((('Operating Model'!$F$7*12)-'Debt Schedule'!$F$23+'Debt Schedule'!$F$25)/(((('Sources & Uses'!$B$5*20)+Assumptions!$B$10)+(('Sources & Uses'!$B$5*20)*Assumptions!$B$17))-(Assumptions!$B$13*'Sources & Uses'!$B$5)-(Assumptions!$B$8*Assumptions!$B$18)))^(1/Assumptions!$B$24)-1),NA()) -> 0.020127691 | F10: =IFERROR((((('Operating Model'!$F$7*15)-'Debt Schedule'!$F$23+'Debt Schedule'!$F$25)/(((('Sources & Uses'!$B$5*20)+Assumptions!$B$10)+(('Sources & Uses'!$B$5*20)*Assumptions!$B$17))-(Assumptions!$B$13*'Sources & Uses'!$B$5)-(Assumptions!$B$8*Assumptions!$B$18)))^(1/Assumptions!$B$24)-1),NA()) -> 0.070014951 | G10: =IFERROR((((('Operating Model'!$F$7*20)-'Debt Schedule'!$F$23+'Debt Schedule'!$F$25)/(((('Sources & Uses'!$B$5*20)+Assumptions!$B$10)+(('Sources & Uses'!$B$5*20)*Assumptions!$B$17))-(Assumptions!$B$13*'Sources & Uses'!$B$5)-(Assumptions!$B$8*Assumptions!$B$18)))^(1/Assumptions!$B$24)-1),NA()) -> 0.13686825
B11: 25.0x | C11: =IFERROR((((('Operating Model'!$F$7*8)-'Debt Schedule'!$F$23+'Debt Schedule'!$F$25)/(((('Sources & Uses'!$B$5*25)+Assumptions!$B$10)+(('Sources & Uses'!$B$5*25)*Assumptions!$B$17))-(Assumptions!$B$13*'Sources & Uses'!$B$5)-(Assumptions!$B$8*Assumptions!$B$18)))^(1/Assumptions!$B$24)-1),NA()) -> -0.11329829 | D11: =IFERROR((((('Operating Model'!$F$7*10)-'Debt Schedule'!$F$23+'Debt Schedule'!$F$25)/(((('Sources & Uses'!$B$5*25)+Assumptions!$B$10)+(('Sources & Uses'!$B$5*25)*Assumptions!$B$17))-(Assumptions!$B$13*'Sources & Uses'!$B$5)-(Assumptions!$B$8*Assumptions!$B$18)))^(1/Assumptions!$B$24)-1),NA()) -> -0.068327416 | E11: =IFERROR((((('Operating Model'!$F$7*12)-'Debt Schedule'!$F$23+'Debt Schedule'!$F$25)/(((('Sources & Uses'!$B$5*25)+Assumptions!$B$10)+(('Sources & Uses'!$B$5*25)*Assumptions!$B$17))-(Assumptions!$B$13*'Sources & Uses'!$B$5)-(Assumptions!$B$8*Assumptions!$B$18)))^(1/Assumptions!$B$24)-1),NA()) -> -0.030664113 | F11: =IFERROR((((('Operating Model'!$F$7*15)-'Debt Schedule'!$F$23+'Debt Schedule'!$F$25)/(((('Sources & Uses'!$B$5*25)+Assumptions!$B$10)+(('Sources & Uses'!$B$5*25)*Assumptions!$B$17))-(Assumptions!$B$13*'Sources & Uses'!$B$5)-(Assumptions!$B$8*Assumptions!$B$18)))^(1/Assumptions!$B$24)-1),NA()) -> 0.016739277 | G11: =IFERROR((((('Operating Model'!$F$7*20)-'Debt Schedule'!$F$23+'Debt Schedule'!$F$25)/(((('Sources & Uses'!$B$5*25)+Assumptions!$B$10)+(('Sources & Uses'!$B$5*25)*Assumptions!$B$17))-(Assumptions!$B$13*'Sources & Uses'!$B$5)-(Assumptions!$B$8*Assumptions!$B$18)))^(1/Assumptions!$B$24)-1),NA()) -> 0.080263974
B12: 33.0x | C12: =IFERROR((((('Operating Model'!$F$7*8)-'Debt Schedule'!$F$23+'Debt Schedule'!$F$25)/(((('Sources & Uses'!$B$5*33)+Assumptions!$B$10)+(('Sources & Uses'!$B$5*33)*Assumptions!$B$17))-(Assumptions!$B$13*'Sources & Uses'!$B$5)-(Assumptions!$B$8*Assumptions!$B$18)))^(1/Assumptions!$B$24)-1),NA()) -> -0.16625589 | D12: =IFERROR((((('Operating Model'!$F$7*10)-'Debt Schedule'!$F$23+'Debt Schedule'!$F$25)/(((('Sources & Uses'!$B$5*33)+Assumptions!$B$10)+(('Sources & Uses'!$B$5*33)*Assumptions!$B$17))-(Assumptions!$B$13*'Sources & Uses'!$B$5)-(Assumptions!$B$8*Assumptions!$B$18)))^(1/Assumptions!$B$24)-1),NA()) -> -0.12397087 | E12: =IFERROR((((('Operating Model'!$F$7*12)-'Debt Schedule'!$F$23+'Debt Schedule'!$F$25)/(((('Sources & Uses'!$B$5*33)+Assumptions!$B$10)+(('Sources & Uses'!$B$5*33)*Assumptions!$B$17))-(Assumptions!$B$13*'Sources & Uses'!$B$5)-(Assumptions!$B$8*Assumptions!$B$18)))^(1/Assumptions!$B$24)-1),NA()) -> -0.088556983 | F12: =IFERROR((((('Operating Model'!$F$7*15)-'Debt Schedule'!$F$23+'Debt Schedule'!$F$25)/(((('Sources & Uses'!$B$5*33)+Assumptions!$B$10)+(('Sources & Uses'!$B$5*33)*Assumptions!$B$17))-(Assumptions!$B$13*'Sources & Uses'!$B$5)-(Assumptions!$B$8*Assumptions!$B$18)))^(1/Assumptions!$B$24)-1),NA()) -> -0.043984725 | G12: =IFERROR((((('Operating Model'!$F$7*20)-'Debt Schedule'!$F$23+'Debt Schedule'!$F$25)/(((('Sources & Uses'!$B$5*33)+Assumptions!$B$10)+(('Sources & Uses'!$B$5*33)*Assumptions!$B$17))-(Assumptions!$B$13*'Sources & Uses'!$B$5)-(Assumptions!$B$8*Assumptions!$B$18)))^(1/Assumptions!$B$24)-1),NA()) -> 0.015746006
A15: Reading the grid
A16: The diagonal (entry = exit, no multiple expansion or contraction) isolates the return from EBITDA growth and deleveraging alone. Columns to the right of the diagonal show upside from multiple expansion; columns to the left show what happens if you have to sell at a discount to what you paid.
