Workbook

Sheet Cover
A1: HAVELLS INDIA LIMITED
A2: Hypothetical Acquisition of IFB Industries Limited: Merger Model & Accretion/Dilution Analysis
A4: WHY THIS DEAL, AND WHY IT IS DIFFERENT FROM THE LBO MODEL
A5: The LBO model elsewhere in this repository models Havells as a hypothetical ACQUISITION TARGET, and states plainly that this is unrealistic given the company's promoter control and scale. This model does the opposite: it models Havells as the ACQUIRER of a real, smaller, publicly listed company. This is a plausible real-world deal shape. Havells is debt-free with a large cash pile, and its Lloyd segment (air conditioners, refrigerators, washing machines) posted a segment loss in FY26 on falling revenue. IFB Industries is a real home-appliance manufacturer (washing machines, microwaves, dishwashers) roughly a fourteenth of Havells' size by market value -- a genuine bolt-on scale. The deal TERMS used here (premium, financing mix, synergies) are entirely illustrative and are not based on any actual announced transaction, advisory mandate, or non-public information about either company.
A13: Acquirer | B13: Havells India Limited (NSE: HAVELLS) -- standalone FY26A financials, consistent with the companion DCF and LBO models in this repo.
A15: Target | B15: IFB Industries Limited (NSE: IFBIND) -- consolidated FY26A financials (home appliances + engineering segments).
A17: Deal structure | B17: Illustrative acquisition of 100% of IFB's outstanding equity at a control premium to its current market price.
A19: Consideration | B19: Base case: 100% cash, funded by a mix of Havells' own balance sheet cash and newly raised acquisition debt -- the company's first-ever borrowing beyond lease liabilities.
A21: Analysis horizon | B21: Year 1 pro forma (illustrative, as if the combination had been in place for the full FY26 year).
A23: Units | B23: INR crore unless stated otherwise
A25: Colour convention | B25: BLUE = hardcoded input (mostly reported figures) | BLACK = formula on this sheet | GREEN = link from another sheet | YELLOW FILL = assumption requiring justification
A27: Disclaimer | B27: Educational exercise. Not investment research, not a deal recommendation, not investment advice, and not based on any actual or rumoured transaction.

Sheet Assumptions
A1: STANDALONE FINANCIALS AND DEAL ASSUMPTIONS
A2: Every yellow cell is an input you own and must justify. Blue cells are reported figures.
A4: HAVELLS (ACQUIRER) -- FY26A STANDALONE, CLEAN
A5: Clean operating EBIT (ex fair-value gain, ex exceptional item) | B5: 1784 | D5: EBITDA 2,213 less D&A 429, consistent with the companion DCF model's treatment of the Goldi Solar fair-value gain.
A6: Other income, net | B6: 204 | D6: Reported FY26A other income.
A7: Existing finance cost (lease interest) | B7: 37 | D7: Reported FY26A finance cost; Havells carries no borrowings today.
A8: Effective tax rate | B8: 0.252 | D8: Statutory rate under the concessional regime, same as the companion models.
A9: Diluted shares outstanding (crore) | B9: 62.7 | D9: Same as the companion DCF and LBO models.
A10: Current share price (INR) | B10: 1190 | D10: Same valuation date as the companion models.
A12: IFB INDUSTRIES (TARGET) -- FY26A CONSOLIDATED, AS REPORTED
A13: Reported profit before tax | B13: 192.45 | D13: FY26A consolidated PBT, as reported.
A14: Reported net profit | B14: 143.56 | D14: FY26A consolidated net profit, as reported.
A15: Effective tax rate (reported) | B15: =1-B14/B13 -> 0.25404001
A16: Estimated net finance cost (verify against annual report) | B16: 20 | D16: Not separately disclosed in the results summary used to build this model. Placeholder: confirm against IFB's FY26 annual report finance-cost note before presenting this model.
A17: Adjusted EBIT (PBT + estimated finance cost) | B17: =B13+B16 -> 212.45
A18: Diluted shares outstanding (crore) | B18: 4.05 | D18: Derived as reported net profit / reported EPS (Rs 35.43).
A19: Current share price (INR) | B19: 1300 | D19: Implied from FY26A market capitalisation (~INR 5,268 Cr) / diluted shares.
A21: DEAL TERMS
A22: Control premium over IFB's current share price | B22: 0.25 | D22: Illustrative; typical control premiums in Indian strategic M&A run 20-40%.
A23: Offer price per IFB share (INR) | B23: =B19*(1+B22) -> 1625
A24: Cash consideration (% of deal) | B24: 1 | D24: Base case: all-cash. Vary this on the Sensitivity tab to test a stock-funded alternative.
A25: Cash drawn from Havells' existing balance sheet | B25: 1500 | D25: Deliberately less than Havells' full FY26A cash balance (INR 2,351 Cr) -- unlike the LBO model, this deal retains a cash buffer.
A26: New acquisition debt: interest rate (all-in) | B26: 0.095 | D26: Priced better than the LBO model's 10.5% -- an investment-grade strategic acquirer borrowing on its own strong balance sheet commands a better rate than a leveraged sponsor deal.
A27: Foregone interest rate on cash used to fund the deal | B27: 0.065 | D27: Illustrative short-term liquid-fund / FD yield opportunity cost.
A28: Transaction fees (% of equity purchase price) | B28: 0.015 | D28: Advisory, legal and financing fees.
A30: PURCHASE PRICE ALLOCATION (SIMPLIFIED)
A31: % of equity purchase price allocated to amortisable intangibles | B31: 0.15 | D31: Simplification: the remainder is allocated to non-amortising goodwill. A full PPA would also step up inventory and fixed assets; this model does not.
A32: Intangible amortisation period (years) | B32: 10 | D32: Illustrative useful life for acquired brand/customer relationships.
A33: Incremental D&A tax-deductible? | B33: No | D33: Assumption: this is a share purchase, so the acquirer does not receive a stepped-up tax basis in India -- the incremental book D&A from the step-up is therefore NOT tax-deductible. This is a real technical nuance between share deals and asset deals worth knowing for an M&A interview.
A35: SYNERGIES
A36: Run-rate annual pre-tax cost synergies | B36: 100 | D36: Illustrative: combined distribution network and manufacturing/procurement scale across the two companies' white-goods lines. Not based on any actual synergy study.
A37: Year 1 realisation (% of run-rate) | B37: 0.5 | D37: Standard first-year phase-in assumption; full run-rate typically takes 18-24 months.

Sheet Sources & Uses
A1: SOURCES & USES
A2: The two columns must tie out exactly. INR crore.
A4: USES
A5: IFB diluted shares (crore) | B5: =Assumptions!$B$18 -> 4.05
A6: x Offer price per share (INR) | B6: =Assumptions!$B$23 -> 1625
A7: Equity purchase price | B7: =B5*B6 -> 6581.25
A8: Transaction fees | B8: =B7*Assumptions!$B$28 -> 98.71875
A9: TOTAL USES | B9: =B7+B8 -> 6679.9688
A12: SOURCES
A13: Cash consideration (% of deal) | B13: =Assumptions!$B$24 -> 1
A14: Total cash portion of the deal | B14: =B9*B13 -> 6679.9688
A15: of which: from Havells' existing balance sheet | B15: =MIN(Assumptions!$B$25,B14) -> 1500
A16: of which: new acquisition term loan (plug) | B16: =B14-B15 -> 5179.9688
A17: Stock portion of the deal (new Havells shares issued) | B17: =B9*(1-B13) -> 0
A18: new Havells shares issued (crore) | B18: =B17/Assumptions!$B$10 -> 0
A19: TOTAL SOURCES | B19: =B15+B16+B17 -> 6679.9688
A21: CHECK (Sources - Uses, must be zero) | B21: =B19-B9 -> 0
A24: Implied acquisition leverage (new debt / Havells FY26A EBITDA of 2,213) | B24: =B16/2213 -> 2.3406998
A25: Implied premium check: offer price vs. current IFB price | B25: =B6/Assumptions!$B$19-1 -> 0.25

Sheet Purchase Price Allocation
A1: PURCHASE PRICE ALLOCATION (SIMPLIFIED)
A2: A full PPA also steps up inventory and fixed assets and recognises deferred tax on the step-up; this model simplifies to a single amortisable intangible plus goodwill, which is enough to demonstrate the accretion/dilution mechanics without over-building a first merger model.
A4: Equity purchase price | B4: ='Sources & Uses'!$B$7 -> 6581.25
A5: x % allocated to amortisable intangibles | B5: =Assumptions!$B$31 -> 0.15
A6: Amortisable intangible asset | B6: =B4*B5 -> 987.1875
A7: Goodwill (residual, non-amortising) | B7: =B4-B6 -> 5594.0625
A9: Amortisation period (years) | B9: =Assumptions!$B$32 -> 10
A10: Incremental annual D&A from the step-up | B10: =B6/B9 -> 98.71875
A11: Tax-deductible? | B11: =Assumptions!$B$33 -> No
A12: NOTE
A13: This is a share purchase, so Havells does not receive a stepped-up tax basis in the target's assets under Indian tax law. The incremental book D&A above reduces reported (book) profit but creates no cash tax benefit -- this model applies tax at the standard rate to book pre-tax profit throughout, which is the standard simplification in a first accretion/dilution model; a more complete model would track book-tax differences and deferred tax separately.

Sheet Pro Forma Income Statement
A1: PRO FORMA INCOME STATEMENT -- YEAR 1 (ILLUSTRATIVE)
A2: As if the two companies had been combined for the full FY26 year. INR crore.
A4: Havells clean operating EBIT | B4: =Assumptions!$B$5 -> 1784
A5: IFB adjusted EBIT | B5: =Assumptions!$B$17 -> 212.45
A6: Combined operating EBIT | B6: =B4+B5 -> 1996.45
A8: Add: Havells other income | B8: =Assumptions!$B$6 -> 204
A9: Less: Havells existing finance cost (lease interest) | B9: =-Assumptions!$B$7 -> -37
A10: Less: IFB existing finance cost (assumed retained) | B10: =-Assumptions!$B$16 -> -20
A12: Add: run-rate synergies realised in Year 1 | B12: =Sensitivity!$B$4 -> 50
A13: Less: incremental D&A from intangible step-up | B13: =-'Purchase Price Allocation'!$B$10 -> -98.71875
A14: Less: interest on new acquisition debt | B14: =-'Sources & Uses'!$B$16*Assumptions!$B$26 -> -492.09703
A15: Less: foregone interest income on cash used to fund the deal | B15: =-'Sources & Uses'!$B$15*Assumptions!$B$27 -> -97.5
A17: PRO FORMA PROFIT BEFORE TAX | B17: =SUM(B6,B8:B10,B12:B15) -> 1505.1342
A18: Less: tax at group effective rate | B18: =-B17*Assumptions!$B$8 -> -379.29382
A19: PRO FORMA NET INCOME | B19: =B17+B18 -> 1125.8404
A21: Pro forma diluted shares (Havells existing + new shares issued) | B21: =Assumptions!$B$9+'Sources & Uses'!$B$18 -> 62.7
A22: PRO FORMA EPS (INR) | B22: =B19/B21 -> 17.955987

Sheet Accretion-Dilution
A1: ACCRETION / DILUTION SUMMARY
A2: Year 1, illustrative. This is the single number an M&A banker is asked for first.
A4: Havells standalone EPS (INR) | B4: =(Assumptions!$B$5+Assumptions!$B$6-Assumptions!$B$7)*(1-Assumptions!$B$8)/Assumptions!$B$9 -> 23.275088
A5: Pro forma combined EPS (INR) | B5: ='Pro Forma Income Statement'!$B$22 -> 17.955987
A6: Accretion / (Dilution) | B6: =B5/B4-1 -> -0.22853192
A9: READING THIS RESULT
A10: A negative number means the deal is DILUTIVE: combined Year 1 EPS is lower than Havells would have earned standing alone, even though no value is destroyed strategically. That happens whenever the after-tax cost of the consideration and financing exceeds the after-tax earnings the target contributes -- which is common for a rich-multiple acquisition (IFB trades near 36x trailing earnings) funded partly with debt priced above the target's own earnings yield. A dilutive deal is not automatically a bad deal: strategic rationale (here, fixing Lloyd's competitive scale in white goods) can justify near-term dilution if the acquirer believes synergies or growth will close the gap over time. See the Sensitivity tab for what it would take to break even.

Sheet Sensitivity
A1: SENSITIVITY & BREAKEVEN SYNERGIES
A2: Row B4 drives the Year 1 synergy figure used on the Pro Forma Income Statement tab -- change it directly, or read it off the grid below.
A4: Year 1 realised synergies (feeds Pro Forma tab) | B4: =Assumptions!$B$36*Assumptions!$B$37 -> 50
A7: GRID: CASH % OF DEAL (columns) x SYNERGY REALISATION (rows) -- Year 1 accretion/(dilution)
B9: Synergy % \ Cash % | C9: 0% | D9: 25% | E9: 50% | F9: 75% | G9: 100%
B10: 0% | C10: =IFERROR((((Assumptions!$B$5+Assumptions!$B$17+Assumptions!$B$6-Assumptions!$B$7-Assumptions!$B$16+(Assumptions!$B$36*0)-'Purchase Price Allocation'!$B$10-(('Sources & Uses'!$B$9*0)-MIN(Assumptions!$B$25,('Sources & Uses'!$B$9*0)))*Assumptions!$B$26-MIN(Assumptions!$B$25,('Sources & Uses'!$B$9*0))*Assumptions!$B$27)*(1-Assumptions!$B$8))/(Assumptions!$B$9+(('Sources & Uses'!$B$9*(1-0))/Assumptions!$B$10)))/'Accretion-Dilution'!$B$4-1,NA()) -> -0.038076614 | D10: =IFERROR((((Assumptions!$B$5+Assumptions!$B$17+Assumptions!$B$6-Assumptions!$B$7-Assumptions!$B$16+(Assumptions!$B$36*0)-'Purchase Price Allocation'!$B$10-(('Sources & Uses'!$B$9*0.25)-MIN(Assumptions!$B$25,('Sources & Uses'!$B$9*0.25)))*Assumptions!$B$26-MIN(Assumptions!$B$25,('Sources & Uses'!$B$9*0.25))*Assumptions!$B$27)*(1-Assumptions!$B$8))/(Assumptions!$B$9+(('Sources & Uses'!$B$9*(1-0.25))/Assumptions!$B$10)))/'Accretion-Dilution'!$B$4-1,NA()) -> -0.072487998 | E10: =IFERROR((((Assumptions!$B$5+Assumptions!$B$17+Assumptions!$B$6-Assumptions!$B$7-Assumptions!$B$16+(Assumptions!$B$36*0)-'Purchase Price Allocation'!$B$10-(('Sources & Uses'!$B$9*0.5)-MIN(Assumptions!$B$25,('Sources & Uses'!$B$9*0.5)))*Assumptions!$B$26-MIN(Assumptions!$B$25,('Sources & Uses'!$B$9*0.5))*Assumptions!$B$27)*(1-Assumptions!$B$8))/(Assumptions!$B$9+(('Sources & Uses'!$B$9*(1-0.5))/Assumptions!$B$10)))/'Accretion-Dilution'!$B$4-1,NA()) -> -0.13045062 | F10: =IFERROR((((Assumptions!$B$5+Assumptions!$B$17+Assumptions!$B$6-Assumptions!$B$7-Assumptions!$B$16+(Assumptions!$B$36*0)-'Purchase Price Allocation'!$B$10-(('Sources & Uses'!$B$9*0.75)-MIN(Assumptions!$B$25,('Sources & Uses'!$B$9*0.75)))*Assumptions!$B$26-MIN(Assumptions!$B$25,('Sources & Uses'!$B$9*0.75))*Assumptions!$B$27)*(1-Assumptions!$B$8))/(Assumptions!$B$9+(('Sources & Uses'!$B$9*(1-0.75))/Assumptions!$B$10)))/'Accretion-Dilution'!$B$4-1,NA()) -> -0.19095109 | G10: =IFERROR((((Assumptions!$B$5+Assumptions!$B$17+Assumptions!$B$6-Assumptions!$B$7-Assumptions!$B$16+(Assumptions!$B$36*0)-'Purchase Price Allocation'!$B$10-(('Sources & Uses'!$B$9*1)-MIN(Assumptions!$B$25,('Sources & Uses'!$B$9*1)))*Assumptions!$B$26-MIN(Assumptions!$B$25,('Sources & Uses'!$B$9*1))*Assumptions!$B$27)*(1-Assumptions!$B$8))/(Assumptions!$B$9+(('Sources & Uses'!$B$9*(1-1))/Assumptions!$B$10)))/'Accretion-Dilution'!$B$4-1,NA()) -> -0.25415981
B11: 25% | C11: =IFERROR((((Assumptions!$B$5+Assumptions!$B$17+Assumptions!$B$6-Assumptions!$B$7-Assumptions!$B$16+(Assumptions!$B$36*0.25)-'Purchase Price Allocation'!$B$10-(('Sources & Uses'!$B$9*0)-MIN(Assumptions!$B$25,('Sources & Uses'!$B$9*0)))*Assumptions!$B$26-MIN(Assumptions!$B$25,('Sources & Uses'!$B$9*0))*Assumptions!$B$27)*(1-Assumptions!$B$8))/(Assumptions!$B$9+(('Sources & Uses'!$B$9*(1-0))/Assumptions!$B$10)))/'Accretion-Dilution'!$B$4-1,NA()) -> -0.026315614 | D11: =IFERROR((((Assumptions!$B$5+Assumptions!$B$17+Assumptions!$B$6-Assumptions!$B$7-Assumptions!$B$16+(Assumptions!$B$36*0.25)-'Purchase Price Allocation'!$B$10-(('Sources & Uses'!$B$9*0.25)-MIN(Assumptions!$B$25,('Sources & Uses'!$B$9*0.25)))*Assumptions!$B$26-MIN(Assumptions!$B$25,('Sources & Uses'!$B$9*0.25))*Assumptions!$B$27)*(1-Assumptions!$B$8))/(Assumptions!$B$9+(('Sources & Uses'!$B$9*(1-0.25))/Assumptions!$B$10)))/'Accretion-Dilution'!$B$4-1,NA()) -> -0.060480326 | E11: =IFERROR((((Assumptions!$B$5+Assumptions!$B$17+Assumptions!$B$6-Assumptions!$B$7-Assumptions!$B$16+(Assumptions!$B$36*0.25)-'Purchase Price Allocation'!$B$10-(('Sources & Uses'!$B$9*0.5)-MIN(Assumptions!$B$25,('Sources & Uses'!$B$9*0.5)))*Assumptions!$B$26-MIN(Assumptions!$B$25,('Sources & Uses'!$B$9*0.5))*Assumptions!$B$27)*(1-Assumptions!$B$8))/(Assumptions!$B$9+(('Sources & Uses'!$B$9*(1-0.5))/Assumptions!$B$10)))/'Accretion-Dilution'!$B$4-1,NA()) -> -0.11818571 | F11: =IFERROR((((Assumptions!$B$5+Assumptions!$B$17+Assumptions!$B$6-Assumptions!$B$7-Assumptions!$B$16+(Assumptions!$B$36*0.25)-'Purchase Price Allocation'!$B$10-(('Sources & Uses'!$B$9*0.75)-MIN(Assumptions!$B$25,('Sources & Uses'!$B$9*0.75)))*Assumptions!$B$26-MIN(Assumptions!$B$25,('Sources & Uses'!$B$9*0.75))*Assumptions!$B$27)*(1-Assumptions!$B$8))/(Assumptions!$B$9+(('Sources & Uses'!$B$9*(1-0.75))/Assumptions!$B$10)))/'Accretion-Dilution'!$B$4-1,NA()) -> -0.17841767 | G11: =IFERROR((((Assumptions!$B$5+Assumptions!$B$17+Assumptions!$B$6-Assumptions!$B$7-Assumptions!$B$16+(Assumptions!$B$36*0.25)-'Purchase Price Allocation'!$B$10-(('Sources & Uses'!$B$9*1)-MIN(Assumptions!$B$25,('Sources & Uses'!$B$9*1)))*Assumptions!$B$26-MIN(Assumptions!$B$25,('Sources & Uses'!$B$9*1))*Assumptions!$B$27)*(1-Assumptions!$B$8))/(Assumptions!$B$9+(('Sources & Uses'!$B$9*(1-1))/Assumptions!$B$10)))/'Accretion-Dilution'!$B$4-1,NA()) -> -0.24134586
B12: 50% | C12: =IFERROR((((Assumptions!$B$5+Assumptions!$B$17+Assumptions!$B$6-Assumptions!$B$7-Assumptions!$B$16+(Assumptions!$B$36*0.5)-'Purchase Price Allocation'!$B$10-(('Sources & Uses'!$B$9*0)-MIN(Assumptions!$B$25,('Sources & Uses'!$B$9*0)))*Assumptions!$B$26-MIN(Assumptions!$B$25,('Sources & Uses'!$B$9*0))*Assumptions!$B$27)*(1-Assumptions!$B$8))/(Assumptions!$B$9+(('Sources & Uses'!$B$9*(1-0))/Assumptions!$B$10)))/'Accretion-Dilution'!$B$4-1,NA()) -> -0.014554613 | D12: =IFERROR((((Assumptions!$B$5+Assumptions!$B$17+Assumptions!$B$6-Assumptions!$B$7-Assumptions!$B$16+(Assumptions!$B$36*0.5)-'Purchase Price Allocation'!$B$10-(('Sources & Uses'!$B$9*0.25)-MIN(Assumptions!$B$25,('Sources & Uses'!$B$9*0.25)))*Assumptions!$B$26-MIN(Assumptions!$B$25,('Sources & Uses'!$B$9*0.25))*Assumptions!$B$27)*(1-Assumptions!$B$8))/(Assumptions!$B$9+(('Sources & Uses'!$B$9*(1-0.25))/Assumptions!$B$10)))/'Accretion-Dilution'!$B$4-1,NA()) -> -0.048472653 | E12: =IFERROR((((Assumptions!$B$5+Assumptions!$B$17+Assumptions!$B$6-Assumptions!$B$7-Assumptions!$B$16+(Assumptions!$B$36*0.5)-'Purchase Price Allocation'!$B$10-(('Sources & Uses'!$B$9*0.5)-MIN(Assumptions!$B$25,('Sources & Uses'!$B$9*0.5)))*Assumptions!$B$26-MIN(Assumptions!$B$25,('Sources & Uses'!$B$9*0.5))*Assumptions!$B$27)*(1-Assumptions!$B$8))/(Assumptions!$B$9+(('Sources & Uses'!$B$9*(1-0.5))/Assumptions!$B$10)))/'Accretion-Dilution'!$B$4-1,NA()) -> -0.1059208 | F12: =IFERROR((((Assumptions!$B$5+Assumptions!$B$17+Assumptions!$B$6-Assumptions!$B$7-Assumptions!$B$16+(Assumptions!$B$36*0.5)-'Purchase Price Allocation'!$B$10-(('Sources & Uses'!$B$9*0.75)-MIN(Assumptions!$B$25,('Sources & Uses'!$B$9*0.75)))*Assumptions!$B$26-MIN(Assumptions!$B$25,('Sources & Uses'!$B$9*0.75))*Assumptions!$B$27)*(1-Assumptions!$B$8))/(Assumptions!$B$9+(('Sources & Uses'!$B$9*(1-0.75))/Assumptions!$B$10)))/'Accretion-Dilution'!$B$4-1,NA()) -> -0.16588425 | G12: =IFERROR((((Assumptions!$B$5+Assumptions!$B$17+Assumptions!$B$6-Assumptions!$B$7-Assumptions!$B$16+(Assumptions!$B$36*0.5)-'Purchase Price Allocation'!$B$10-(('Sources & Uses'!$B$9*1)-MIN(Assumptions!$B$25,('Sources & Uses'!$B$9*1)))*Assumptions!$B$26-MIN(Assumptions!$B$25,('Sources & Uses'!$B$9*1))*Assumptions!$B$27)*(1-Assumptions!$B$8))/(Assumptions!$B$9+(('Sources & Uses'!$B$9*(1-1))/Assumptions!$B$10)))/'Accretion-Dilution'!$B$4-1,NA()) -> -0.22853192
B13: 75% | C13: =IFERROR((((Assumptions!$B$5+Assumptions!$B$17+Assumptions!$B$6-Assumptions!$B$7-Assumptions!$B$16+(Assumptions!$B$36*0.75)-'Purchase Price Allocation'!$B$10-(('Sources & Uses'!$B$9*0)-MIN(Assumptions!$B$25,('Sources & Uses'!$B$9*0)))*Assumptions!$B$26-MIN(Assumptions!$B$25,('Sources & Uses'!$B$9*0))*Assumptions!$B$27)*(1-Assumptions!$B$8))/(Assumptions!$B$9+(('Sources & Uses'!$B$9*(1-0))/Assumptions!$B$10)))/'Accretion-Dilution'!$B$4-1,NA()) -> -0.0027936133 | D13: =IFERROR((((Assumptions!$B$5+Assumptions!$B$17+Assumptions!$B$6-Assumptions!$B$7-Assumptions!$B$16+(Assumptions!$B$36*0.75)-'Purchase Price Allocation'!$B$10-(('Sources & Uses'!$B$9*0.25)-MIN(Assumptions!$B$25,('Sources & Uses'!$B$9*0.25)))*Assumptions!$B$26-MIN(Assumptions!$B$25,('Sources & Uses'!$B$9*0.25))*Assumptions!$B$27)*(1-Assumptions!$B$8))/(Assumptions!$B$9+(('Sources & Uses'!$B$9*(1-0.25))/Assumptions!$B$10)))/'Accretion-Dilution'!$B$4-1,NA()) -> -0.036464981 | E13: =IFERROR((((Assumptions!$B$5+Assumptions!$B$17+Assumptions!$B$6-Assumptions!$B$7-Assumptions!$B$16+(Assumptions!$B$36*0.75)-'Purchase Price Allocation'!$B$10-(('Sources & Uses'!$B$9*0.5)-MIN(Assumptions!$B$25,('Sources & Uses'!$B$9*0.5)))*Assumptions!$B$26-MIN(Assumptions!$B$25,('Sources & Uses'!$B$9*0.5))*Assumptions!$B$27)*(1-Assumptions!$B$8))/(Assumptions!$B$9+(('Sources & Uses'!$B$9*(1-0.5))/Assumptions!$B$10)))/'Accretion-Dilution'!$B$4-1,NA()) -> -0.093655881 | F13: =IFERROR((((Assumptions!$B$5+Assumptions!$B$17+Assumptions!$B$6-Assumptions!$B$7-Assumptions!$B$16+(Assumptions!$B$36*0.75)-'Purchase Price Allocation'!$B$10-(('Sources & Uses'!$B$9*0.75)-MIN(Assumptions!$B$25,('Sources & Uses'!$B$9*0.75)))*Assumptions!$B$26-MIN(Assumptions!$B$25,('Sources & Uses'!$B$9*0.75))*Assumptions!$B$27)*(1-Assumptions!$B$8))/(Assumptions!$B$9+(('Sources & Uses'!$B$9*(1-0.75))/Assumptions!$B$10)))/'Accretion-Dilution'!$B$4-1,NA()) -> -0.15335084 | G13: =IFERROR((((Assumptions!$B$5+Assumptions!$B$17+Assumptions!$B$6-Assumptions!$B$7-Assumptions!$B$16+(Assumptions!$B$36*0.75)-'Purchase Price Allocation'!$B$10-(('Sources & Uses'!$B$9*1)-MIN(Assumptions!$B$25,('Sources & Uses'!$B$9*1)))*Assumptions!$B$26-MIN(Assumptions!$B$25,('Sources & Uses'!$B$9*1))*Assumptions!$B$27)*(1-Assumptions!$B$8))/(Assumptions!$B$9+(('Sources & Uses'!$B$9*(1-1))/Assumptions!$B$10)))/'Accretion-Dilution'!$B$4-1,NA()) -> -0.21571798
B14: 100% | C14: =IFERROR((((Assumptions!$B$5+Assumptions!$B$17+Assumptions!$B$6-Assumptions!$B$7-Assumptions!$B$16+(Assumptions!$B$36*1)-'Purchase Price Allocation'!$B$10-(('Sources & Uses'!$B$9*0)-MIN(Assumptions!$B$25,('Sources & Uses'!$B$9*0)))*Assumptions!$B$26-MIN(Assumptions!$B$25,('Sources & Uses'!$B$9*0))*Assumptions!$B$27)*(1-Assumptions!$B$8))/(Assumptions!$B$9+(('Sources & Uses'!$B$9*(1-0))/Assumptions!$B$10)))/'Accretion-Dilution'!$B$4-1,NA()) -> 0.008967387 | D14: =IFERROR((((Assumptions!$B$5+Assumptions!$B$17+Assumptions!$B$6-Assumptions!$B$7-Assumptions!$B$16+(Assumptions!$B$36*1)-'Purchase Price Allocation'!$B$10-(('Sources & Uses'!$B$9*0.25)-MIN(Assumptions!$B$25,('Sources & Uses'!$B$9*0.25)))*Assumptions!$B$26-MIN(Assumptions!$B$25,('Sources & Uses'!$B$9*0.25))*Assumptions!$B$27)*(1-Assumptions!$B$8))/(Assumptions!$B$9+(('Sources & Uses'!$B$9*(1-0.25))/Assumptions!$B$10)))/'Accretion-Dilution'!$B$4-1,NA()) -> -0.024457309 | E14: =IFERROR((((Assumptions!$B$5+Assumptions!$B$17+Assumptions!$B$6-Assumptions!$B$7-Assumptions!$B$16+(Assumptions!$B$36*1)-'Purchase Price Allocation'!$B$10-(('Sources & Uses'!$B$9*0.5)-MIN(Assumptions!$B$25,('Sources & Uses'!$B$9*0.5)))*Assumptions!$B$26-MIN(Assumptions!$B$25,('Sources & Uses'!$B$9*0.5))*Assumptions!$B$27)*(1-Assumptions!$B$8))/(Assumptions!$B$9+(('Sources & Uses'!$B$9*(1-0.5))/Assumptions!$B$10)))/'Accretion-Dilution'!$B$4-1,NA()) -> -0.081390968 | F14: =IFERROR((((Assumptions!$B$5+Assumptions!$B$17+Assumptions!$B$6-Assumptions!$B$7-Assumptions!$B$16+(Assumptions!$B$36*1)-'Purchase Price Allocation'!$B$10-(('Sources & Uses'!$B$9*0.75)-MIN(Assumptions!$B$25,('Sources & Uses'!$B$9*0.75)))*Assumptions!$B$26-MIN(Assumptions!$B$25,('Sources & Uses'!$B$9*0.75))*Assumptions!$B$27)*(1-Assumptions!$B$8))/(Assumptions!$B$9+(('Sources & Uses'!$B$9*(1-0.75))/Assumptions!$B$10)))/'Accretion-Dilution'!$B$4-1,NA()) -> -0.14081742 | G14: =IFERROR((((Assumptions!$B$5+Assumptions!$B$17+Assumptions!$B$6-Assumptions!$B$7-Assumptions!$B$16+(Assumptions!$B$36*1)-'Purchase Price Allocation'!$B$10-(('Sources & Uses'!$B$9*1)-MIN(Assumptions!$B$25,('Sources & Uses'!$B$9*1)))*Assumptions!$B$26-MIN(Assumptions!$B$25,('Sources & Uses'!$B$9*1))*Assumptions!$B$27)*(1-Assumptions!$B$8))/(Assumptions!$B$9+(('Sources & Uses'!$B$9*(1-1))/Assumptions!$B$10)))/'Accretion-Dilution'!$B$4-1,NA()) -> -0.20290404
A17: BREAKEVEN SYNERGIES (closed-form)
A18: Run-rate pre-tax synergies needed to make the base-case deal (100% cash, as structured on Sources & Uses) exactly EPS-neutral in Year 1:
A20: Required pro forma PBT for EPS neutrality | B20: ='Accretion-Dilution'!$B$4*Assumptions!$B$9/(1-Assumptions!$B$8) -> 1951
A21: Pro forma PBT at zero Year 1 synergies | B21: =Assumptions!$B$5+Assumptions!$B$17+Assumptions!$B$6-Assumptions!$B$7-Assumptions!$B$16-'Purchase Price Allocation'!$B$10-'Sources & Uses'!$B$16*Assumptions!$B$26-'Sources & Uses'!$B$15*Assumptions!$B$27 -> 1455.1342
A22: Gap to close (= required Year 1 synergy contribution) | B22: =B20-B21 -> 495.86578
A23: Implied required RUN-RATE synergies (Year 1 gap / realisation %) | B23: =B22/Assumptions!$B$37 -> 991.73156
A24: vs. the illustrative run-rate synergy assumption actually used | B24: =Assumptions!$B$36 -> 100
